{
	"animations": [
		{
			"loop": false,
			"offsets": [
				-3,
				5
			],
			"anim": "hey",
			"fps": 24,
			"name": "BF HEY",
			"indices": []
		},
		{
			"loop": false,
			"offsets": [
				15,
				18
			],
			"anim": "hurt",
			"fps": 24,
			"name": "BF hit",
			"indices": []
		},
		{
			"loop": true,
			"offsets": [
				-4,
				0
			],
			"anim": "scared",
			"fps": 24,
			"name": "BF idle shaking",
			"indices": []
		},
		{
			"loop": false,
			"offsets": [
				37,
				11
			],
			"anim": "firstDeath",
			"fps": 24,
			"name": "BF dies",
			"indices": []
		},
		{
			"loop": true,
			"offsets": [
				37,
				5
			],
			"anim": "deathLoop",
			"fps": 24,
			"name": "BF Dead Loop",
			"indices": []
		},
		{
			"loop": false,
			"offsets": [
				37,
				69
			],
			"anim": "deathConfirm",
			"fps": 24,
			"name": "BF Dead confirm",
			"indices": []
		},
		{
			"loop": false,
			"offsets": [
				-10,
				-16
			],
			"anim": "dodge",
			"fps": 24,
			"name": "boyfriend dodge",
			"indices": []
		},
		{
			"loop": false,
			"offsets": [
				294,
				267
			],
			"anim": "attack",
			"fps": 24,
			"name": "boyfriend attack",
			"indices": []
		},
		{
			"loop": false,
			"offsets": [
				-40,
				-40
			],
			"anim": "pre-attack",
			"fps": 24,
			"name": "bf pre attack",
			"indices": []
		},
		{
			"loop": false,
			"offsets": [
				-13,
				17
			],
			"anim": "singLEFTmiss",
			"fps": 24,
			"name": "Miss Left",
			"indices": []
		},
		{
			"loop": false,
			"offsets": [
				-36,
				-63
			],
			"anim": "singDOWNmiss",
			"fps": 24,
			"name": "Miss Down",
			"indices": []
		},
		{
			"loop": false,
			"offsets": [
				-48,
				12
			],
			"anim": "singUPmiss",
			"fps": 24,
			"name": "Miss Up",
			"indices": []
		},
		{
			"loop": false,
			"offsets": [
				-46,
				5
			],
			"anim": "singRIGHTmiss",
			"fps": 24,
			"name": "Miss Right",
			"indices": []
		},
		{
			"offsets": [
				-5,
				1
			],
			"indices": [],
			"fps": 24,
			"anim": "idle",
			"loop": false,
			"name": "BF idle"
		},
		{
			"offsets": [
				-8,
				4
			],
			"indices": [],
			"fps": 24,
			"anim": "singLEFT",
			"loop": false,
			"name": "BF NOTE LEFT0"
		},
		{
			"offsets": [
				-8,
				-7
			],
			"indices": [],
			"fps": 24,
			"anim": "singDOWN",
			"loop": false,
			"name": "BF NOTE DOWN0"
		},
		{
			"offsets": [
				-11,
				11
			],
			"indices": [],
			"fps": 24,
			"anim": "singUP",
			"loop": false,
			"name": "BF NOTE UP0"
		},
		{
			"offsets": [
				-9,
				2
			],
			"indices": [],
			"fps": 24,
			"anim": "singRIGHT",
			"loop": false,
			"name": "BF NOTE RIGHT0"
		}
	],
	"no_antialiasing": false,
	"image": "characters/BOYFRIENDremix",
	"position": [
		0,
		350
	],
	"healthicon": "bf",
	"flip_x": true,
	"healthbar_colors": [
		49,
		176,
		209
	],
	"camera_position": [
		340,
		0
	],
	"sing_duration": 4,
	"scale": 1
}