{
	"animations": [
		{
			"loop": true,
			"offsets": [
				0,
				0
			],
			"anim": "idle",
			"fps": 24,
			"name": "OGFlip Idle",
			"indices": []
		},
		{
			"loop": false,
			"offsets": [
				3,
				21
			],
			"anim": "singUP",
			"fps": 24,
			"name": "OGFlip M UP",
			"indices": []
		},
		{
			"loop": false,
			"offsets": [
				-132,
				-13
			],
			"anim": "singRIGHT",
			"fps": 24,
			"name": "OGFlip M RIGHT",
			"indices": []
		},
		{
			"loop": false,
			"offsets": [
				-24,
				-56
			],
			"anim": "singDOWN",
			"fps": 24,
			"name": "OGFlip M DOWN",
			"indices": []
		},
		{
			"loop": false,
			"offsets": [
				59,
				14
			],
			"anim": "singLEFT",
			"fps": 24,
			"name": "OGFlip M LEFT",
			"indices": []
		}
	],
	"no_antialiasing": false,
	"image": "characters/FLIPPY_alt",
	"position": [
		-200,
		300
	],
	"healthicon": "flippy",
	"flip_x": false,
	"healthbar_colors": [
		215,
		255,
		167
	],
	"camera_position": [
		170,
		-60
	],
	"sing_duration": 4,
	"scale": 1
}